.flake8
.gitignore
README.md
requirements.txt
setup.py
tox.ini
.circleci/config.yml
percentiles/__init__.py
percentiles/percentiles.py
percentiles.egg-info/PKG-INFO
percentiles.egg-info/SOURCES.txt
percentiles.egg-info/dependency_links.txt
percentiles.egg-info/not-zip-safe
percentiles.egg-info/top_level.txt
test/test_percentiles.py