Metadata-Version: 2.1
Name: percentiles
Version: 0.2.2
Summary: Get percentile of sequence without numpy
Home-page: https://github.com/heaviss/percentiles
Author: Vladimir Seregin
Author-email: 31631@rambler.ru
License: MIT
Keywords: percentile,statistics
Platform: UNKNOWN
Classifier: Programming Language :: Python :: 2.7
Classifier: Programming Language :: Python :: 3
Classifier: License :: OSI Approved :: MIT License
Classifier: Operating System :: OS Independent
